example/__init__.py
example/example.py
medusa_logger/__init__.py
medusa_logger/decorator.py
medusa_logger/encoder.py
medusa_logger/logger.py
tests/__init__.py
tests/test_decorator.py
tests/test_encoder.py
tests/test_logger.py
medusa_logger-1.3.1.dist-info/LICENSE
medusa_logger-1.3.1.dist-info/METADATA
medusa_logger-1.3.1.dist-info/WHEEL
medusa_logger-1.3.1.dist-info/top_level.txt
medusa_logger-1.3.1.dist-info/RECORD
