Metadata-Version: 2.1
Name: medusa-logger
Version: 1.3.1
Summary: A logging utility package with colored logs.
Home-page: UNKNOWN
License: UNKNOWN
Platform: UNKNOWN
License-File: LICENSE
Requires-Dist: coloredlogs
